mmv_regionseg/__init__.py
mmv_regionseg/_widget.py
mmv_regionseg/napari.yaml
mmv_regionseg/_tests/__init__.py
mmv_regionseg/_tests/test_widget.py
mmv_regionseg-0.4.0.dist-info/licenses/LICENSE
mmv_regionseg-0.4.0.dist-info/METADATA
mmv_regionseg-0.4.0.dist-info/WHEEL
mmv_regionseg-0.4.0.dist-info/entry_points.txt
mmv_regionseg-0.4.0.dist-info/top_level.txt
mmv_regionseg-0.4.0.dist-info/RECORD
