Metadata-Version: 2.4
Name: mmv-regionseg
Version: 0.4.0
Summary: Napari plugin for the segmentation of regions by flood
Author-email: Peter Lampen <lampen@isas.de>
License: 
Project-URL: Homepage, https://github.com/MMV-Lab/mmv-regionseg
Project-URL: Bug Tracker, https://github.com/MMV-Lab/mmv-regionseg/issues
Project-URL: Documentation, https://github.com/MMV-Lab/mmv-regionseg#README.md
Project-URL: Source Code, https://github.com/MMV-Lab/mmv-regionseg
Project-URL: User Support, https://github.com/MMV-Lab/mmv-regionseg/issues
Classifier: Development Status :: 3 - Alpha
Classifier: Intended Audience :: Science/Research
Classifier: Framework :: napari
Classifier: Topic :: Scientific/Engineering :: Image Processing
Classifier: Programming Language :: Python
Classifier: Programming Language :: Python :: 3
Classifier: Programming Language :: Python :: 3.9
Classifier: Programming Language :: Python :: 3.10
Classifier: Programming Language :: Python :: 3.11
Classifier: Programming Language :: Python :: 3.12
Classifier: Operating System :: OS Independent
Classifier: License :: OSI Approved :: BSD License
Requires-Python: >=3.9
License-File: LICENSE
Requires-Dist: napari<0.6.0,>=0.5.0
Requires-Dist: numpy<2.0,>=1.23
Requires-Dist: qtpy>=2.0
Requires-Dist: scikit-image>=0.20
Requires-Dist: tifffile>=2023.2.28
Provides-Extra: qt
Requires-Dist: pyqt5>=5.15; extra == "qt"
Provides-Extra: testing
Requires-Dist: tox>=4.0; extra == "testing"
Requires-Dist: pytest>=7.0; extra == "testing"
Requires-Dist: pytest-cov>=4.0; extra == "testing"
Requires-Dist: pytest-qt>=4.0; extra == "testing"
Dynamic: license-file
